capcruncher_tools-0.2.1.dist-info/METADATA
capcruncher_tools-0.2.1.dist-info/WHEEL
capcruncher_tools-0.2.1.dist-info/entry_points.txt
capcruncher_tools-0.2.1.dist-info/license_files/LICENSE
capcruncher_tools/__init__.py
capcruncher_tools/api.py
capcruncher_tools/cli.py
capcruncher_tools/count.py
capcruncher_tools/capcruncher_tools.abi3.so
capcruncher_tools-0.2.1.dist-info/RECORD
