Metadata-Version: 2.1
Name: capcruncher-tools
Version: 0.2.1
License-File: LICENSE
Summary: Extra utilities to enhance CapCruncher
Author: asmith
Author-email: alastair.smith@ndcls.ox.ac.uk
Requires-Python: >=3.8
Project-URL: repository, https://github.com/alsmith151/CapCruncherTools
